bayesim/__init__.py
bayesim/__main__.py
bayesim/model.py
bayesim/params.py
bayesim/pmf.py
bayesim/six.py
bayesim/utils.py
bayesim-0.10.2.dist-info/LICENSE
bayesim-0.10.2.dist-info/METADATA
bayesim-0.10.2.dist-info/WHEEL
bayesim-0.10.2.dist-info/entry_points.txt
bayesim-0.10.2.dist-info/top_level.txt
bayesim-0.10.2.dist-info/RECORD
