Metadata-Version: 2.1
Name: bayesim
Version: 0.10.2
Summary: Fast model fitting via Bayesian inference
Author: Rachel Kurchin, Giuseppe Romano
Author-email: rkurchin@alum.mit.edu, romanog@mit.edu
License: GPLv2
Classifier: Programming Language :: Python :: 3.7
License-File: LICENSE
Requires-Dist: pandas
Requires-Dist: scipy
Requires-Dist: matplotlib
Requires-Dist: joblib
Requires-Dist: tables
